{"frames": {

"radar-0.png":
{
	"frame": {"x":1,"y":1,"w":64,"h":64},
	"rotated": false,
	"trimmed": false,
	"spriteSourceSize": {"x":0,"y":0,"w":64,"h":64},
	"sourceSize": {"w":64,"h":64}
},
"radar-1.png":
{
	"frame": {"x":1,"y":67,"w":64,"h":64},
	"rotated": false,
	"trimmed": false,
	"spriteSourceSize": {"x":0,"y":0,"w":64,"h":64},
	"sourceSize": {"w":64,"h":64}
},
"radar-2.png":
{
	"frame": {"x":1,"y":133,"w":64,"h":64},
	"rotated": false,
	"trimmed": false,
	"spriteSourceSize": {"x":0,"y":0,"w":64,"h":64},
	"sourceSize": {"w":64,"h":64}
},
"radar-3.png":
{
	"frame": {"x":67,"y":1,"w":64,"h":64},
	"rotated": false,
	"trimmed": false,
	"spriteSourceSize": {"x":0,"y":0,"w":64,"h":64},
	"sourceSize": {"w":64,"h":64}
},
"radar-4.png":
{
	"frame": {"x":133,"y":1,"w":64,"h":64},
	"rotated": false,
	"trimmed": false,
	"spriteSourceSize": {"x":0,"y":0,"w":64,"h":64},
	"sourceSize": {"w":64,"h":64}
},
"radar-5.png":
{
	"frame": {"x":67,"y":67,"w":64,"h":64},
	"rotated": false,
	"trimmed": false,
	"spriteSourceSize": {"x":0,"y":0,"w":64,"h":64},
	"sourceSize": {"w":64,"h":64}
},
"radar-6.png":
{
	"frame": {"x":67,"y":133,"w":64,"h":64},
	"rotated": false,
	"trimmed": false,
	"spriteSourceSize": {"x":0,"y":0,"w":64,"h":64},
	"sourceSize": {"w":64,"h":64}
},
"radar-7.png":
{
	"frame": {"x":133,"y":67,"w":64,"h":64},
	"rotated": false,
	"trimmed": false,
	"spriteSourceSize": {"x":0,"y":0,"w":64,"h":64},
	"sourceSize": {"w":64,"h":64}
}},
"meta": {
	"app": "https://www.codeandweb.com/texturepacker",
	"version": "1.0",
	"image": "radar.png",
	"format": "RGBA8888",
	"size": {"w":198,"h":198},
	"scale": "1",
	"smartupdate": "$TexturePacker:SmartUpdate:186d3e41feb6f10cb3af7d8fbb0a2257:a1250f05e2104ed09b4b794b39002a5e:d24a0c7da565b1bc334a325903634001$"
}
}
